{
  "Studio Benx": ["Cabeleireiro"],
  "Cinemark": ["Cinema", "Etretenimento"],
  "Gscell Acessorios": ["Eletronicos"],
  "Hotmart": ["Estudo"],
  "Eco Jordao": ["Lazer"],
  "Portal da Cidade": ["Outros"],
  "Mercado Livre": ["Outros"],
  "Bijumaster Comercio": ["Outros"],
  "ifood Padaria": ["Padaria"],
  "Paes e Doces Trigosu": ["Padaria"],
  "Pizzaria Bella Arte": ["Restaurante"],
  "ifood Restaurante": ["Restaurante"],
  "Maria das Gracas Rios": ["Restaurante"],
  "Estancia Grill": ["Restaurante"],
  "Quebrada Burger": ["Restaurante"],
  "Johnny Rockets": ["Restaurante"],
  "Baiao de II Cachoeirinha": ["Restaurante"],
  "Pag*Coquelicotparis": ["Restaurante"],
  "Pag*Emporioserraa": ["Restaurante"],
  "Pag*Saborettos": ["Restaurante"],
  "Grupo Gennius": ["Restaurante"],
  "Drogaria Atacadão": ["Saude"],
  "Dentista": ["Saude"],
  "Humanas Academia": ["Saude"],
  "Droga Barao": ["Saude"],
  "Nubank": ["Seguro"],
  "TIM": ["Servicos"],
  "Pag*Daletereboucas": ["Servicos"],
  "A Toca": ["Servicos"],
  "Amazon Music": ["Streaming"],
  "Amazon prime": ["Streaming"],
  "Atacadão": ["Supermercado"],
  "Extra": ["Supermercado"],
  "ifood Mercado": ["Supermercado"],
  "Andorinha": ["Supermercado"],
  "99app": ["Transporte"],
  "Uber": ["Transporte"],
  "Shein": ["Vestuario"],
  "Puma": ["Vestuario"],
  "Authentic Feet": ["Vestuario"],
  "Decinel": ["Vestuario"],
  "C&A": ["Vestuario"],
  "Htm*Canteexcelparc": ["Sem Categoria"],
  "Viviana Patricia De Pa": ["Sem Categoria"],
  "Pag*Amorearte": ["Sem Categoria"],
  "depósito de confiança": ["Estorno"],
  "estorno de": ["Estorno"],
  "+": ["Estorno"]
}
